{"orderbooks":[{"baseAsset":"TATA","bids":[{"price":1002.9,"quantity":1,"orderId":"4075k7tzn94wpaf0zwg49","filled":0,"side":"buy","userId":"5"},{"price":1002.4,"quantity":1,"orderId":"i89wl4tpqv0eh21bxzoogo","filled":0,"side":"buy","userId":"5"},{"price":1002.8,"quantity":1,"orderId":"b7rs5ngyt3i6rjwsjhyrlw","filled":0,"side":"buy","userId":"5"},{"price":1002.4,"quantity":1,"orderId":"ad72b60dw74a3yml31nsbr","filled":0,"side":"buy","userId":"5"},{"price":1002.7,"quantity":1,"orderId":"a4mg0s7e81435b0uq8go1q","filled":0,"side":"buy","userId":"5"},{"price":1002.5,"quantity":1,"orderId":"lq52x7osaxnqpp6ccs32kn","filled":0,"side":"buy","userId":"5"},{"price":1003,"quantity":1,"orderId":"i7lemprdw7hlyze4lio7e","filled":0,"side":"buy","userId":"5"},{"price":1002.8,"quantity":1,"orderId":"839qs4lk3narf5wmuqr9nc","filled":0,"side":"buy","userId":"5"},{"price":1008.8,"quantity":1,"orderId":"obexabofof9qh6lnqsdv","filled":0,"side":"buy","userId":"5"},{"price":1008.6,"quantity":1,"orderId":"mz835eh7fco8qgkcprfrg","filled":0,"side":"buy","userId":"5"},{"price":1008.4,"quantity":1,"orderId":"tlkhalmrgid20q5xoti3sj","filled":0,"side":"buy","userId":"5"},{"price":1008.5,"quantity":1,"orderId":"rb9b6719yubew93q0h08","filled":0,"side":"buy","userId":"5"},{"price":1008.2,"quantity":1,"orderId":"d8e0be8ypq3ugq1rhxwfo","filled":0,"side":"buy","userId":"5"},{"price":1008.7,"quantity":1,"orderId":"z9ltx85xbwd580uhda3jox","filled":0,"side":"buy","userId":"5"},{"price":1008.6,"quantity":1,"orderId":"1c9b1d8rhw413cwko4o6hb","filled":0,"side":"buy","userId":"5"}],"asks":[{"price":6000,"quantity":1,"orderId":"sdf55uetwtut3a28mhc4","filled":0,"side":"sell","userId":"1"},{"price":6000,"quantity":1,"orderId":"bb8usj9yyqdqxbdlp180s","filled":0,"side":"sell","userId":"1"},{"price":1009.6,"quantity":1,"orderId":"4ox6cu1g3redbdd2a2y4dv","filled":0,"side":"sell","userId":"5"},{"price":1009.9,"quantity":1,"orderId":"pr1r1c5ra6z1totl0y90e","filled":0,"side":"sell","userId":"5"},{"price":1009.6,"quantity":1,"orderId":"onvcikpd5chzqetgiihxp","filled":0,"side":"sell","userId":"5"},{"price":1009.8,"quantity":1,"orderId":"jd3adn78dpp0n935s8dxplc","filled":0,"side":"sell","userId":"5"},{"price":1009.4,"quantity":1,"orderId":"l3fq1zpzvawqmtx7fwhhe","filled":0,"side":"sell","userId":"5"},{"price":1009.9,"quantity":1,"orderId":"avp39ovkt2k7yasyfav8c","filled":0,"side":"sell","userId":"5"},{"price":1009.2,"quantity":1,"orderId":"dgxgp5w4exlutqkmz7q24","filled":0,"side":"sell","userId":"5"},{"price":1010.1,"quantity":1,"orderId":"qc33w7a66kryibnnmruni","filled":0,"side":"sell","userId":"5"},{"price":1009.5,"quantity":1,"orderId":"z4xo4vperjaqtnlv5q6khi","filled":0,"side":"sell","userId":"5"}],"lastTradeId":41,"currentPrice":0}],"balances":[["1",{"INR":{"available":9942120,"locked":3},"TATA":{"available":9999994,"locked":2}}],["2",{"INR":{"available":10000000,"locked":0},"TATA":{"available":10000000,"locked":0}}],["5",{"INR":{"available":10029192.2,"locked":28684.799999999992},"TATA":{"available":9999590,"locked":414}}]]}